MANIFEST.in
README
README.md
setup.py
processcall/__init__.py
processcall/processcall.py
processcall.egg-info/PKG-INFO
processcall.egg-info/SOURCES.txt
processcall.egg-info/dependency_links.txt
processcall.egg-info/top_level.txt