Metadata-Version: 1.1
Name: processcall
Version: 1.1.0
Summary: a simple subprocess manager,suport stream stdout \ async 
Home-page: https://github.com/rfyiamcool/simpleprocess
Author: ruifengyun
Author-email: rfyiamcool@163.com
License: MIT
Keywords: subprocess processcall,fengyun
Platform: UNKNOWN
Classifier: Development Status :: 6 - Mature
Classifier: Intended Audience :: Developers
Classifier: License :: OSI Approved :: MIT License
Classifier: Programming Language :: Python :: 2.7
Classifier: Programming Language :: Python :: 3.0
Classifier: Topic :: Software Development :: Libraries :: Python Modules
